airdb/__init__.py
airdb/data/README.md
air_db-0.0.6.dist-info/LICENSE
air_db-0.0.6.dist-info/METADATA
air_db-0.0.6.dist-info/WHEEL
air_db-0.0.6.dist-info/top_level.txt
air_db-0.0.6.dist-info/RECORD
