Metadata-Version: 2.1
Name: air-db
Version: 0.0.6
Summary: A data access layer for atmospheric time series datasets
Home-page: https://github.com/isezen/air-db
Download-URL: https://pypi.org/project/air-db/#files
Author: Ismail SEZEN
Author-email: sezenismail@gmail.com
License: AGPLv3
Project-URL: Bug Tracker, https://github.com/isezen/air-db/issues
Project-URL: Documentation, https://github.com/isezen/air-db/wiki
Project-URL: Source Code, https://github.com/isezen/air-db
Keywords: data,environment,pollutant,meteorology,turkey
Platform: linux
Platform: darwin
Platform: windows
Classifier: Development Status :: 2 - Pre-Alpha
Classifier: Environment :: Console
Classifier: Intended Audience :: Developers
Classifier: Intended Audience :: Science/Research
Classifier: Operating System :: OS Independent
Classifier: License :: OSI Approved :: GNU Affero General Public License v3 or later (AGPLv3+)
Classifier: Programming Language :: Python :: 3.6
Classifier: Programming Language :: Python :: 3.7
Classifier: Programming Language :: Python :: 3.8
Classifier: Topic :: Utilities
Requires-Python: >=3.6
License-File: LICENSE
Requires-Dist: pandas
Requires-Dist: numpy
Requires-Dist: xarray
